{
    "topics": {
      "reflections": [
        {"term": "Reflection", "definition": "Definition of reflection"},
        {"term": "Mirror", "definition": "Definition of mirror"}
      ],
      "rotations": [
        {"term": "Rotation", "definition": "Definition of rotation"},
        {"term": "Axis", "definition": "Definition of axis"}
      ],
      "translations": [
        {"term": "Translation", "definition": "Definition of translation"},
        {"term": "Vertical Rule", "definition": "Definition of vertical rule"}
      ],
      "congruency": [
        {"term": "Congruent", "definition": "Definition of congruent"},
        {"term": "Similar", "definition": "Definition of similar"}
      ]
    }
  }